privacy_analytics/__init__.py
privacy_analytics/admin.py
privacy_analytics/apps.py
privacy_analytics/middleware.py
privacy_analytics/models.py
privacy_analytics/tests.py
privacy_analytics/urls.py
privacy_analytics/util.py
privacy_analytics/views.py
privacy_analytics/migrations/0001_initial.py
privacy_analytics/migrations/0002_auto_20190926_2029.py
privacy_analytics/migrations/__init__.py
privacy_analytics/templates/privacy_analytics/base.html
privacy_analytics/templates/privacy_analytics/dashboard.html
django_privacy_analytics-0.1.1.dist-info/LICENSE
django_privacy_analytics-0.1.1.dist-info/METADATA
django_privacy_analytics-0.1.1.dist-info/WHEEL
django_privacy_analytics-0.1.1.dist-info/top_level.txt
django_privacy_analytics-0.1.1.dist-info/RECORD
