Metadata-Version: 2.1
Name: django-privacy-analytics
Version: 0.1.1
Summary: Privacy-focused, performant, and server-side analytics for your Django project
Home-page: https://github.com/milesmcc/django-privacy-analytics/
Author: R. Miles McCain
Author-email: opensource@sendmiles.email
License: MIT
Platform: UNKNOWN
Classifier: Environment :: Web Environment
Classifier: Framework :: Django
Classifier: Framework :: Django :: 2.2
Classifier: Intended Audience :: Developers
Classifier: License :: OSI Approved :: BSD License
Classifier: Operating System :: OS Independent
Classifier: Programming Language :: Python
Classifier: Programming Language :: Python :: 3.5
Classifier: Programming Language :: Python :: 3.6
Classifier: Topic :: Internet :: WWW/HTTP
Classifier: Topic :: Internet :: WWW/HTTP :: Dynamic Content
